LICENCE.txt
MANIFEST.in
README.rst
setup.cfg
setup.py
boussole/__init__.py
boussole/compiler.py
boussole/exceptions.py
boussole/finder.py
boussole/inspector.py
boussole/logs.py
boussole/parser.py
boussole/project.py
boussole/resolver.py
boussole/watcher.py
boussole.egg-info/PKG-INFO
boussole.egg-info/SOURCES.txt
boussole.egg-info/dependency_links.txt
boussole.egg-info/entry_points.txt
boussole.egg-info/requires.txt
boussole.egg-info/top_level.txt
boussole.egg-info/zip-safe
boussole/cli/__init__.py
boussole/cli/compile.py
boussole/cli/console_script.py
boussole/cli/startproject.py
boussole/cli/version.py
boussole/cli/watch.py
boussole/conf/__init__.py
boussole/conf/base_backend.py
boussole/conf/discovery.py
boussole/conf/json_backend.py
boussole/conf/model.py
boussole/conf/post_processor.py
boussole/conf/yaml_backend.py
foundation_toast/__init__.py
foundation_toast/pages/__init__.py
foundation_toast/pages/index.py
foundation_toast/settings/__init__.py
foundation_toast/settings/production.py
foundation_toast/settings/webassets_filters.py