Metadata-Version: 2.1
Name: boussole
Version: 1.5.1
Summary: Commandline interface to build Sass projects using libsass-python
Home-page: https://github.com/sveetch/boussole
Author: David Thenon
Author-email: sveetch@gmail.com
License: MIT
Keywords: Scss,Sass,Libsass,watchdog
Platform: UNKNOWN
Classifier: License :: OSI Approved :: MIT License
Classifier: Operating System :: OS Independent
Classifier: Development Status :: 5 - Production/Stable
Classifier: Environment :: Console
Classifier: Programming Language :: Python
Classifier: Programming Language :: Python :: 2.7
Classifier: Programming Language :: Python :: 3.5
Classifier: Intended Audience :: Developers
Classifier: Topic :: Internet
Classifier: Topic :: Software Development :: Compilers
Classifier: Topic :: Software Development :: Libraries :: Python Modules
Provides-Extra: dev
